gfxcanvas/__init__.py
gfxcanvas/core.py
gfxcanvas-1.0.0.dist-info/licenses/LICENSE
gfxcanvas-1.0.0.dist-info/METADATA
gfxcanvas-1.0.0.dist-info/WHEEL
gfxcanvas-1.0.0.dist-info/top_level.txt
gfxcanvas-1.0.0.dist-info/RECORD
