Metadata-Version: 2.4
Name: gfxcanvas
Version: 1.0.0
Summary: Simple Python Graphics and Game Engine
Home-page: https://github.com/basitganie/gfxcanvas
Author: Basit Ahmad Ganie
Author-email: Basit Ahmad Ganie <basitahmed1412@gmail.com>
License: MIT
Project-URL: Homepage, https://github.com/basitganie/gfxcanvas
Project-URL: Documentation, https://github.com/basitganie/gfxcanvas#readme
Project-URL: Repository, https://github.com/basitganie/gfxcanvas
Project-URL: Bug Tracker, https://github.com/basitganie/gfxcanvas/issues
Keywords: graphics,game-engine,tkinter,canvas,animation,physics,2d,3d,sprites
Classifier: Development Status :: 4 - Beta
Classifier: Intended Audience :: Developers
Classifier: Topic :: Software Development :: Libraries :: Python Modules
Classifier: Topic :: Multimedia :: Graphics
Classifier: Topic :: Games/Entertainment
Classifier: License :: OSI Approved :: MIT License
Classifier: Programming Language :: Python :: 3
Classifier: Programming Language :: Python :: 3.7
Classifier: Programming Language :: Python :: 3.8
Classifier: Programming Language :: Python :: 3.9
Classifier: Programming Language :: Python :: 3.10
Classifier: Programming Language :: Python :: 3.11
Classifier: Operating System :: OS Independent
Requires-Python: >=3.7
License-File: LICENSE
Requires-Dist: Pillow>=9.0.0
Dynamic: author
Dynamic: home-page
Dynamic: license-file
Dynamic: requires-python
